CONTRIBUTING.rst
LICENSE
MANIFEST.in
README.md
setup.cfg
setup.py
prepared_properties/__init__.py
prepared_properties/prepared_properties.py
prepared_properties.egg-info/PKG-INFO
prepared_properties.egg-info/SOURCES.txt
prepared_properties.egg-info/dependency_links.txt
prepared_properties.egg-info/not-zip-safe
prepared_properties.egg-info/requires.txt
prepared_properties.egg-info/top_level.txt
tests/__init__.py
tests/test_prepared_properties.py