Metadata-Version: 2.1
Name: prepared-properties
Version: 1.0.2
Summary: Declarative annotations and prefetches for Django models
Home-page: https://github.com/robinramael/prepared_properties
Author: Robin Ramael
Author-email: robin.ramael@gmail.com
License: GNU General Public License v3
Keywords: prepared_properties
Platform: UNKNOWN
Classifier: Intended Audience :: Developers
Classifier: License :: OSI Approved :: GNU General Public License v3 (GPLv3)
Classifier: Natural Language :: English
Classifier: Programming Language :: Python :: 3
Classifier: Programming Language :: Python :: 3.6
Classifier: Programming Language :: Python :: 3.7
Classifier: Programming Language :: Python :: 3.8
Requires-Python: >=3.6
